README.md
setup.py
colab2notebook/__init__.py
colab2notebook/generate_token.py
colab2notebook/ip_finder.py
colab2notebook/notebook_starter.py
colab2notebook/notebook_stopper.py
colab2notebook/notebook_url.py
colab2notebook/output_generator.py
colab2notebook.egg-info/PKG-INFO
colab2notebook.egg-info/SOURCES.txt
colab2notebook.egg-info/dependency_links.txt
colab2notebook.egg-info/top_level.txt