Metadata-Version: 2.1
Name: colab2notebook
Version: 1.0.2
Summary: Jupyter Notebook on Google Colab
Author: Muhammad Ali
Author-email: malirashid1994@gmail.com
